mcp_server_jira/__init__.py
mcp_server_jira/__main__.py
mcp_server_jira/server.py
mcp_server_jira-0.1.1.dist-info/METADATA
mcp_server_jira-0.1.1.dist-info/WHEEL
mcp_server_jira-0.1.1.dist-info/entry_points.txt
mcp_server_jira-0.1.1.dist-info/licenses/LICENSE
mcp_server_jira-0.1.1.dist-info/RECORD
