Metadata-Version: 2.4
Name: mcp-server-jira
Version: 0.1.1
Summary: A Model Context Protocol server providing Jira integration tools for LLMs
Project-URL: Homepage, https://github.com/your-username/mcp-jira-v3
Project-URL: Repository, https://github.com/your-username/mcp-jira-v3
Project-URL: Issues, https://github.com/your-username/mcp-jira-v3/issues
Project-URL: Documentation, https://github.com/your-username/mcp-jira-v3#readme
Project-URL: Changelog, https://github.com/your-username/mcp-jira-v3/releases
Author-email: Your Name <your-email@example.com>
License: MIT
License-File: LICENSE
Keywords: atlassian,automation,issues,jira,jql,llm,mcp,model-context-protocol,transitions,worklog
Classifier: Development Status :: 4 - Beta
Classifier: Environment :: Console
Classifier: Intended Audience :: Developers
Classifier: License :: OSI Approved :: MIT License
Classifier: Operating System :: OS Independent
Classifier: Programming Language :: Python :: 3
Classifier: Programming Language :: Python :: 3.10
Classifier: Programming Language :: Python :: 3.11
Classifier: Programming Language :: Python :: 3.12
Classifier: Topic :: Internet :: WWW/HTTP :: Dynamic Content
Classifier: Topic :: Office/Business
Classifier: Topic :: Software Development :: Libraries :: Python Modules
Classifier: Topic :: System :: Systems Administration
Requires-Python: >=3.10
Requires-Dist: httpx>=0.25.0
Requires-Dist: mcp>=1.0.0
Requires-Dist: pydantic>=2.0.0
